econml/__init__.py
econml/_cate_estimator.py
econml/_ortho_learner.py
econml/_shap.py
econml/_tree_exporter.py
econml/_version.py
econml/bootstrap.py
econml/causal_forest.py
econml/deepiv.py
econml/dowhy.py
econml/drlearner.py
econml/ortho_forest.py
econml/ortho_iv.py
econml/two_stage_least_squares.py
econml/utilities.py
econml/_ensemble/__init__.py
econml/_ensemble/_ensemble.py
econml/_ensemble/_utilities.py
econml/automated_ml/__init__.py
econml/automated_ml/_automated_ml.py
econml/cate_interpreter/__init__.py
econml/cate_interpreter/_interpreters.py
econml/data/__init__.py
econml/data/dgps.py
econml/data/dynamic_panel_dgp.py
econml/data/ihdp/example.csv
econml/data/ihdp/example_full.csv
econml/data/ihdp/sim.csv
econml/data/input_dynamicdgp/cov_new.jbl
econml/data/input_dynamicdgp/gm_0.jbl
econml/data/input_dynamicdgp/gm_1.jbl
econml/data/input_dynamicdgp/gm_2.jbl
econml/data/input_dynamicdgp/gm_3.jbl
econml/data/input_dynamicdgp/gm_4.jbl
econml/data/input_dynamicdgp/gm_5.jbl
econml/data/input_dynamicdgp/gm_6.jbl
econml/data/input_dynamicdgp/lognorm_neg_0.jbl
econml/data/input_dynamicdgp/lognorm_neg_1.jbl
econml/data/input_dynamicdgp/lognorm_neg_2.jbl
econml/data/input_dynamicdgp/lognorm_neg_3.jbl
econml/data/input_dynamicdgp/lognorm_neg_4.jbl
econml/data/input_dynamicdgp/lognorm_neg_5.jbl
econml/data/input_dynamicdgp/lognorm_pos_0.jbl
econml/data/input_dynamicdgp/lognorm_pos_1.jbl
econml/data/input_dynamicdgp/lognorm_pos_2.jbl
econml/data/input_dynamicdgp/lognorm_pos_3.jbl
econml/data/input_dynamicdgp/lognorm_pos_4.jbl
econml/data/input_dynamicdgp/lognorm_pos_5.jbl
econml/data/input_dynamicdgp/lognorm_pos_6.jbl
econml/data/input_dynamicdgp/n_0.jbl
econml/data/input_dynamicdgp/n_1.jbl
econml/data/input_dynamicdgp/n_2.jbl
econml/data/input_dynamicdgp/n_3.jbl
econml/data/input_dynamicdgp/n_4.jbl
econml/data/input_dynamicdgp/n_5.jbl
econml/data/input_dynamicdgp/n_6.jbl
econml/dml/__init__.py
econml/dml/_rlearner.py
econml/dml/causal_forest.py
econml/dml/dml.py
FIRSTBEATLU-0.13.1.dist-info/LICENSE
FIRSTBEATLU-0.13.1.dist-info/METADATA
FIRSTBEATLU-0.13.1.dist-info/WHEEL
FIRSTBEATLU-0.13.1.dist-info/top_level.txt
FIRSTBEATLU-0.13.1.dist-info/RECORD
